paho/__init__.py
paho/mqtt/__init__.py
paho/mqtt/client.py
paho/mqtt/matcher.py
paho/mqtt/packettypes.py
paho/mqtt/properties.py
paho/mqtt/publish.py
paho/mqtt/reasoncodes.py
paho/mqtt/subscribe.py
paho/mqtt/subscribeoptions.py
iottalk_paho_mqtt-1.5.1.dist-info/LICENSE.txt
iottalk_paho_mqtt-1.5.1.dist-info/METADATA
iottalk_paho_mqtt-1.5.1.dist-info/WHEEL
iottalk_paho_mqtt-1.5.1.dist-info/top_level.txt
iottalk_paho_mqtt-1.5.1.dist-info/RECORD
