Metadata-Version: 2.1
Name: iottalk-paho-mqtt
Version: 1.5.1
Summary: MQTT version 5.0/3.1.1 client class
Home-page: http://eclipse.org/paho
Author: Roger Light
Author-email: roger@atchoo.org
License: Eclipse Public License v1.0 / Eclipse Distribution License v1.0
Keywords: paho
Platform: UNKNOWN
Classifier: Development Status :: 4 - Beta
Classifier: Intended Audience :: Developers
Classifier: License :: OSI Approved
Classifier: Operating System :: MacOS :: MacOS X
Classifier: Operating System :: Microsoft :: Windows
Classifier: Operating System :: POSIX
Classifier: Natural Language :: English
Classifier: Programming Language :: Python
Classifier: Programming Language :: Python :: 2
Classifier: Programming Language :: Python :: 2.7
Classifier: Programming Language :: Python :: 3
Classifier: Programming Language :: Python :: 3.5
Classifier: Programming Language :: Python :: 3.6
Classifier: Programming Language :: Python :: 3.7
Classifier: Programming Language :: Python :: 3.8
Classifier: Topic :: Communications
Classifier: Topic :: Internet
Provides-Extra: proxy
Requires-Dist: PySocks ; extra == 'proxy'
